standardstreams/__init__.py
standardstreams/exceptions.py
standardstreams/library.py
standardstreams/settings.py
standardstreams-0.2.0.dist-info/DESCRIPTION.rst
standardstreams-0.2.0.dist-info/METADATA
standardstreams-0.2.0.dist-info/RECORD
standardstreams-0.2.0.dist-info/WHEEL
standardstreams-0.2.0.dist-info/metadata.json
standardstreams-0.2.0.dist-info/top_level.txt
