Metadata-Version: 2.0
Name: standardstreams
Version: 0.2.0
Summary: Standard output, standard error, and standard input stream library
Home-page: https://github.com/chrissimpkins/standardstreams
Author: Christopher Simpkins
Author-email: chris@sourcefoundry.org
License: MIT license
Keywords: shell,standard output,standard input,standard error,stream,streams,pipe
Platform: any
Classifier: Development Status :: 2 - Pre-Alpha
Classifier: Natural Language :: English
Classifier: License :: OSI Approved :: MIT License
Classifier: Operating System :: OS Independent
Classifier: Programming Language :: Python
Classifier: Programming Language :: Python :: 2
Classifier: Programming Language :: Python :: 2.6
Classifier: Programming Language :: Python :: 2.7
Classifier: Programming Language :: Python :: 3
Classifier: Programming Language :: Python :: 3.3
Classifier: Programming Language :: Python :: 3.4
Classifier: Programming Language :: Python :: 3.5
Classifier: Topic :: Software Development :: Libraries :: Python Modules
